README.rst
setup.py
pea/__init__.py
pea/context.py
pea/formatter.py
pea.egg-info/PKG-INFO
pea.egg-info/SOURCES.txt
pea.egg-info/dependency_links.txt
pea.egg-info/entry_points.txt
pea.egg-info/requires.txt
pea.egg-info/top_level.txt
tests/__init__.py
tests/test_pea.py
tests/unit/__init__.py
tests/unit/test_context.py
tests/unit/test_formatter.py