Metadata-Version: 1.1
Name: pea
Version: 0.1.2
Summary: minimal BDD library
Home-page: http://github.com/gfxmonk/pea/tree
Author: Tim Cuthbertson
Author-email: tim3d.junk+pea@gmail.com
License: UNKNOWN
Keywords: test nosetests nose nosetest bdd cucumber lettuce
Platform: UNKNOWN
Classifier: License :: OSI Approved :: BSD License
Classifier: Programming Language :: Python
Classifier: Development Status :: 4 - Beta
Classifier: Intended Audience :: Developers
Classifier: Topic :: Software Development :: Libraries :: Python Modules
Classifier: Topic :: Software Development :: Testing
